main.py
bieniciscraper/__init__.py
bieniciscraper/cli.py
bieniciscraper/constants.py
bieniciscraper/main.py
bieniciscraper/scraper.py
bieniciscraper-1.1.3.dist-info/LICENSE
bieniciscraper-1.1.3.dist-info/METADATA
bieniciscraper-1.1.3.dist-info/WHEEL
bieniciscraper-1.1.3.dist-info/entry_points.txt
bieniciscraper-1.1.3.dist-info/top_level.txt
bieniciscraper-1.1.3.dist-info/RECORD
