Metadata-Version: 2.1
Name: bieniciscraper
Version: 1.1.3
Summary: scrape housing listings on bien'ici from any bien'ici search url 💛
Home-page: https://github.com/lobstrio/bieniciscraper
Author: sasha bouloudnine
Author-email: sasha.bouloudnine@lobstr.io
License: UNKNOWN
Platform: UNKNOWN
Classifier: Programming Language :: Python :: 3
Classifier: License :: OSI Approved :: MIT License
Classifier: Operating System :: OS Independent
License-File: LICENSE
Requires-Dist: requests
Requires-Dist: retry
